advlog/__init__.py
advlog/setup.py
advlog/core/__init__.py
advlog/core/config.py
advlog/core/formatter.py
advlog/core/logger.py
advlog/core/logger_temp.py
advlog/handlers/__init__.py
advlog/handlers/console.py
advlog/handlers/file.py
advlog/plugins/__init__.py
advlog/plugins/progress.py
advlog/plugins/training.py
advlog/utils/__init__.py
advlog/utils/console.py
advlog/utils/environment.py
advlog/utils/naming.py
advlog/utils/path.py
advlog/utils/rich_compat.py
advlog_core-0.1.0.dist-info/METADATA
advlog_core-0.1.0.dist-info/WHEEL
advlog_core-0.1.0.dist-info/licenses/LICENSE
advlog_core-0.1.0.dist-info/licenses/NOTICE
advlog_core-0.1.0.dist-info/RECORD
