Metadata-Version: 2.4
Name: advlog-core
Version: 0.1.0
Summary: Advanced logging library with Rich features, progress tracking, and ML training utilities
Project-URL: Homepage, https://github.com/mz-wang/advlog
Project-URL: Documentation, https://github.com/mz-wang/advlog#readme
Project-URL: Repository, https://github.com/mz-wang/advlog
Project-URL: Issues, https://github.com/mz-wang/advlog/issues
Project-URL: Changelog, https://github.com/mz-wang/advlog/blob/main/CHANGELOG.md
Author-email: Mengzhao Wang <mengzhao_wang@foxmail.com>
License: Apache-2.0
License-File: LICENSE
License-File: NOTICE
Keywords: deep-learning,logging,ml,progress,rich,training
Classifier: Development Status :: 4 - Beta
Classifier: Intended Audience :: Developers
Classifier: License :: OSI Approved :: Apache Software License
Classifier: Operating System :: OS Independent
Classifier: Programming Language :: Python :: 3
Classifier: Topic :: Software Development :: Libraries :: Python Modules
Classifier: Topic :: System :: Logging
Requires-Python: >=3.10
Requires-Dist: pre-commit>=4.5.1
Requires-Dist: rich>=10.0.0
Provides-Extra: all
Requires-Dist: accelerate>=0.20.0; extra == 'all'
Requires-Dist: omegaconf>=2.0.0; extra == 'all'
Requires-Dist: torchinfo>=1.0.0; extra == 'all'
Provides-Extra: config
Requires-Dist: omegaconf>=2.0.0; extra == 'config'
Provides-Extra: dev
Requires-Dist: pipreqs>=0.5.0; extra == 'dev'
Requires-Dist: pytest-cov>=4.0.0; extra == 'dev'
Requires-Dist: pytest>=7.0.0; extra == 'dev'
Requires-Dist: ruff>=0.1.0; extra == 'dev'
Requires-Dist: vermin>=1.6.0; extra == 'dev'
Provides-Extra: distributed
Requires-Dist: accelerate>=0.20.0; extra == 'distributed'
Provides-Extra: torch
Requires-Dist: torchinfo>=1.0.0; extra == 'torch'
